{
  "version": "6",
  "dialect": "sqlite",
  "id": "9fc062da-0a00-4085-8721-4beec9d96f71",
  "prevId": "930d15bc-cd38-4be9-94d3-b8c78bdc1c25",
  "tables": {
    "dat_entries": {
      "name": "dat_entries",
      "columns": {
        "id": {
          "name": "id",
          "type": "integer",
          "primaryKey": true,
          "notNull": true,
          "autoincrement": true
        },
        "version_source_id": {
          "name": "version_source_id",
          "type": "integer",
          "primaryKey": false,
          "notNull": true,
          "autoincrement": false
        },
        "game_title": {
          "name": "game_title",
          "type": "text",
          "primaryKey": false,
          "notNull": true,
          "autoincrement": false
        },
        "region": {
          "name": "region",
          "type": "text",
          "primaryKey": false,
          "notNull": false,
          "autoincrement": false
        },
        "revision": {
          "name": "revision",
          "type": "text",
          "primaryKey": false,
          "notNull": false,
          "autoincrement": false
        },
        "crc32": {
          "name": "crc32",
          "type": "text",
          "primaryKey": false,
          "notNull": false,
          "autoincrement": false
        },
        "md5": {
          "name": "md5",
          "type": "text",
          "primaryKey": false,
          "notNull": false,
          "autoincrement": false
        },
        "sha1": {
          "name": "sha1",
          "type": "text",
          "primaryKey": false,
          "notNull": false,
          "autoincrement": false
        }
      },
      "indexes": {
        "dat_entries_version_source_id_idx": {
          "name": "dat_entries_version_source_id_idx",
          "columns": [
            "version_source_id"
          ],
          "isUnique": false
        },
        "dat_entries_crc32_idx": {
          "name": "dat_entries_crc32_idx",
          "columns": [
            "crc32"
          ],
          "isUnique": false
        },
        "dat_entries_sha1_idx": {
          "name": "dat_entries_sha1_idx",
          "columns": [
            "sha1"
          ],
          "isUnique": false
        }
      },
      "foreignKeys": {
        "dat_entries_version_source_id_version_sources_id_fk": {
          "name": "dat_entries_version_source_id_version_sources_id_fk",
          "tableFrom": "dat_entries",
          "tableTo": "version_sources",
          "columnsFrom": [
            "version_source_id"
          ],
          "columnsTo": [
            "id"
          ],
          "onDelete": "cascade",
          "onUpdate": "no action"
        }
      },
      "compositePrimaryKeys": {},
      "uniqueConstraints": {},
      "checkConstraints": {}
    },
    "download_clients": {
      "name": "download_clients",
      "columns": {
        "id": {
          "name": "id",
          "type": "integer",
          "primaryKey": true,
          "notNull": true,
          "autoincrement": true
        },
        "name": {
          "name": "name",
          "type": "text",
          "primaryKey": false,
          "notNull": true,
          "autoincrement": false
        },
        "type": {
          "name": "type",
          "type": "text",
          "primaryKey": false,
          "notNull": true,
          "autoincrement": false
        },
        "url": {
          "name": "url",
          "type": "text",
          "primaryKey": false,
          "notNull": true,
          "autoincrement": false
        },
        "username": {
          "name": "username",
          "type": "text",
          "primaryKey": false,
          "notNull": false,
          "autoincrement": false
        },
        "password": {
          "name": "password",
          "type": "text",
          "primaryKey": false,
          "notNull": false,
          "autoincrement": false
        },
        "download_path": {
          "name": "download_path",
          "type": "text",
          "primaryKey": false,
          "notNull": false,
          "autoincrement": false
        },
        "platform_paths": {
          "name": "platform_paths",
          "type": "text",
          "primaryKey": false,
          "notNull": false,
          "autoincrement": false
        },
        "enabled": {
          "name": "enabled",
          "type": "integer",
          "primaryKey": false,
          "notNull": true,
          "autoincrement": false,
          "default": true
        }
      },
      "indexes": {},
      "foreignKeys": {},
      "compositePrimaryKeys": {},
      "uniqueConstraints": {},
      "checkConstraints": {}
    },
    "download_history": {
      "name": "download_history",
      "columns": {
        "id": {
          "name": "id",
          "type": "integer",
          "primaryKey": true,
          "notNull": true,
          "autoincrement": true
        },
        "game_id": {
          "name": "game_id",
          "type": "integer",
          "primaryKey": false,
          "notNull": true,
          "autoincrement": false
        },
        "indexer_id": {
          "name": "indexer_id",
          "type": "integer",
          "primaryKey": false,
          "notNull": false,
          "autoincrement": false
        },
        "release_title": {
          "name": "release_title",
          "type": "text",
          "primaryKey": false,
          "notNull": false,
          "autoincrement": false
        },
        "size_bytes": {
          "name": "size_bytes",
          "type": "integer",
          "primaryKey": false,
          "notNull": false,
          "autoincrement": false
        },
        "seeders": {
          "name": "seeders",
          "type": "integer",
          "primaryKey": false,
          "notNull": false,
          "autoincrement": false
        },
        "score": {
          "name": "score",
          "type": "integer",
          "primaryKey": false,
          "notNull": false,
          "autoincrement": false
        },
        "download_client_id": {
          "name": "download_client_id",
          "type": "integer",
          "primaryKey": false,
          "notNull": false,
          "autoincrement": false
        },
        "external_id": {
          "name": "external_id",
          "type": "text",
          "primaryKey": false,
          "notNull": false,
          "autoincrement": false
        },
        "started_at": {
          "name": "started_at",
          "type": "text",
          "primaryKey": false,
          "notNull": true,
          "autoincrement": false,
          "default": "(datetime('now'))"
        },
        "completed_at": {
          "name": "completed_at",
          "type": "text",
          "primaryKey": false,
          "notNull": false,
          "autoincrement": false
        },
        "status": {
          "name": "status",
          "type": "text",
          "primaryKey": false,
          "notNull": true,
          "autoincrement": false,
          "default": "'downloading'"
        }
      },
      "indexes": {
        "download_history_game_id_idx": {
          "name": "download_history_game_id_idx",
          "columns": [
            "game_id"
          ],
          "isUnique": false
        }
      },
      "foreignKeys": {
        "download_history_game_id_games_id_fk": {
          "name": "download_history_game_id_games_id_fk",
          "tableFrom": "download_history",
          "tableTo": "games",
          "columnsFrom": [
            "game_id"
          ],
          "columnsTo": [
            "id"
          ],
          "onDelete": "no action",
          "onUpdate": "no action"
        },
        "download_history_indexer_id_indexers_id_fk": {
          "name": "download_history_indexer_id_indexers_id_fk",
          "tableFrom": "download_history",
          "tableTo": "indexers",
          "columnsFrom": [
            "indexer_id"
          ],
          "columnsTo": [
            "id"
          ],
          "onDelete": "no action",
          "onUpdate": "no action"
        },
        "download_history_download_client_id_download_clients_id_fk": {
          "name": "download_history_download_client_id_download_clients_id_fk",
          "tableFrom": "download_history",
          "tableTo": "download_clients",
          "columnsFrom": [
            "download_client_id"
          ],
          "columnsTo": [
            "id"
          ],
          "onDelete": "no action",
          "onUpdate": "no action"
        }
      },
      "compositePrimaryKeys": {},
      "uniqueConstraints": {},
      "checkConstraints": {}
    },
    "game_files": {
      "name": "game_files",
      "columns": {
        "id": {
          "name": "id",
          "type": "integer",
          "primaryKey": true,
          "notNull": true,
          "autoincrement": true
        },
        "game_id": {
          "name": "game_id",
          "type": "integer",
          "primaryKey": false,
          "notNull": true,
          "autoincrement": false
        },
        "path": {
          "name": "path",
          "type": "text",
          "primaryKey": false,
          "notNull": true,
          "autoincrement": false
        },
        "filename": {
          "name": "filename",
          "type": "text",
          "primaryKey": false,
          "notNull": true,
          "autoincrement": false
        },
        "size_bytes": {
          "name": "size_bytes",
          "type": "integer",
          "primaryKey": false,
          "notNull": false,
          "autoincrement": false
        },
        "file_format": {
          "name": "file_format",
          "type": "text",
          "primaryKey": false,
          "notNull": false,
          "autoincrement": false
        },
        "crc32": {
          "name": "crc32",
          "type": "text",
          "primaryKey": false,
          "notNull": false,
          "autoincrement": false
        },
        "md5": {
          "name": "md5",
          "type": "text",
          "primaryKey": false,
          "notNull": false,
          "autoincrement": false
        },
        "sha1": {
          "name": "sha1",
          "type": "text",
          "primaryKey": false,
          "notNull": false,
          "autoincrement": false
        },
        "known_version": {
          "name": "known_version",
          "type": "text",
          "primaryKey": false,
          "notNull": false,
          "autoincrement": false
        },
        "latest_version": {
          "name": "latest_version",
          "type": "text",
          "primaryKey": false,
          "notNull": false,
          "autoincrement": false
        },
        "version_status": {
          "name": "version_status",
          "type": "text",
          "primaryKey": false,
          "notNull": true,
          "autoincrement": false,
          "default": "'unknown'"
        },
        "version_checked_at": {
          "name": "version_checked_at",
          "type": "text",
          "primaryKey": false,
          "notNull": false,
          "autoincrement": false
        },
        "imported_at": {
          "name": "imported_at",
          "type": "text",
          "primaryKey": false,
          "notNull": true,
          "autoincrement": false,
          "default": "(datetime('now'))"
        }
      },
      "indexes": {
        "game_files_game_id_idx": {
          "name": "game_files_game_id_idx",
          "columns": [
            "game_id"
          ],
          "isUnique": false
        },
        "game_files_path_idx": {
          "name": "game_files_path_idx",
          "columns": [
            "path"
          ],
          "isUnique": true
        },
        "game_files_crc32_idx": {
          "name": "game_files_crc32_idx",
          "columns": [
            "crc32"
          ],
          "isUnique": false
        },
        "game_files_sha1_idx": {
          "name": "game_files_sha1_idx",
          "columns": [
            "sha1"
          ],
          "isUnique": false
        }
      },
      "foreignKeys": {
        "game_files_game_id_games_id_fk": {
          "name": "game_files_game_id_games_id_fk",
          "tableFrom": "game_files",
          "tableTo": "games",
          "columnsFrom": [
            "game_id"
          ],
          "columnsTo": [
            "id"
          ],
          "onDelete": "cascade",
          "onUpdate": "no action"
        }
      },
      "compositePrimaryKeys": {},
      "uniqueConstraints": {},
      "checkConstraints": {}
    },
    "games": {
      "name": "games",
      "columns": {
        "id": {
          "name": "id",
          "type": "integer",
          "primaryKey": true,
          "notNull": true,
          "autoincrement": true
        },
        "title": {
          "name": "title",
          "type": "text",
          "primaryKey": false,
          "notNull": true,
          "autoincrement": false
        },
        "igdb_id": {
          "name": "igdb_id",
          "type": "integer",
          "primaryKey": false,
          "notNull": false,
          "autoincrement": false
        },
        "screenscraper_id": {
          "name": "screenscraper_id",
          "type": "integer",
          "primaryKey": false,
          "notNull": false,
          "autoincrement": false
        },
        "platform_id": {
          "name": "platform_id",
          "type": "integer",
          "primaryKey": false,
          "notNull": true,
          "autoincrement": false
        },
        "cover_url": {
          "name": "cover_url",
          "type": "text",
          "primaryKey": false,
          "notNull": false,
          "autoincrement": false
        },
        "description": {
          "name": "description",
          "type": "text",
          "primaryKey": false,
          "notNull": false,
          "autoincrement": false
        },
        "region": {
          "name": "region",
          "type": "text",
          "primaryKey": false,
          "notNull": false,
          "autoincrement": false
        },
        "release_date": {
          "name": "release_date",
          "type": "text",
          "primaryKey": false,
          "notNull": false,
          "autoincrement": false
        },
        "genres": {
          "name": "genres",
          "type": "text",
          "primaryKey": false,
          "notNull": false,
          "autoincrement": false
        },
        "alternate_names": {
          "name": "alternate_names",
          "type": "text",
          "primaryKey": false,
          "notNull": false,
          "autoincrement": false
        },
        "title_id": {
          "name": "title_id",
          "type": "text",
          "primaryKey": false,
          "notNull": false,
          "autoincrement": false
        },
        "created_at": {
          "name": "created_at",
          "type": "text",
          "primaryKey": false,
          "notNull": true,
          "autoincrement": false,
          "default": "(datetime('now'))"
        },
        "updated_at": {
          "name": "updated_at",
          "type": "text",
          "primaryKey": false,
          "notNull": true,
          "autoincrement": false,
          "default": "(datetime('now'))"
        }
      },
      "indexes": {
        "games_igdb_id_idx": {
          "name": "games_igdb_id_idx",
          "columns": [
            "igdb_id"
          ],
          "isUnique": false
        },
        "games_platform_id_idx": {
          "name": "games_platform_id_idx",
          "columns": [
            "platform_id"
          ],
          "isUnique": false
        },
        "games_title_id_idx": {
          "name": "games_title_id_idx",
          "columns": [
            "title_id"
          ],
          "isUnique": false
        }
      },
      "foreignKeys": {
        "games_platform_id_platforms_id_fk": {
          "name": "games_platform_id_platforms_id_fk",
          "tableFrom": "games",
          "tableTo": "platforms",
          "columnsFrom": [
            "platform_id"
          ],
          "columnsTo": [
            "id"
          ],
          "onDelete": "no action",
          "onUpdate": "no action"
        }
      },
      "compositePrimaryKeys": {},
      "uniqueConstraints": {},
      "checkConstraints": {}
    },
    "indexers": {
      "name": "indexers",
      "columns": {
        "id": {
          "name": "id",
          "type": "integer",
          "primaryKey": true,
          "notNull": true,
          "autoincrement": true
        },
        "name": {
          "name": "name",
          "type": "text",
          "primaryKey": false,
          "notNull": true,
          "autoincrement": false
        },
        "type": {
          "name": "type",
          "type": "text",
          "primaryKey": false,
          "notNull": true,
          "autoincrement": false
        },
        "url": {
          "name": "url",
          "type": "text",
          "primaryKey": false,
          "notNull": true,
          "autoincrement": false
        },
        "api_key": {
          "name": "api_key",
          "type": "text",
          "primaryKey": false,
          "notNull": true,
          "autoincrement": false
        },
        "priority": {
          "name": "priority",
          "type": "integer",
          "primaryKey": false,
          "notNull": true,
          "autoincrement": false,
          "default": 50
        },
        "enabled": {
          "name": "enabled",
          "type": "integer",
          "primaryKey": false,
          "notNull": true,
          "autoincrement": false,
          "default": true
        },
        "categories": {
          "name": "categories",
          "type": "text",
          "primaryKey": false,
          "notNull": false,
          "autoincrement": false
        }
      },
      "indexes": {},
      "foreignKeys": {},
      "compositePrimaryKeys": {},
      "uniqueConstraints": {},
      "checkConstraints": {}
    },
    "notification_targets": {
      "name": "notification_targets",
      "columns": {
        "id": {
          "name": "id",
          "type": "integer",
          "primaryKey": true,
          "notNull": true,
          "autoincrement": true
        },
        "name": {
          "name": "name",
          "type": "text",
          "primaryKey": false,
          "notNull": true,
          "autoincrement": false
        },
        "type": {
          "name": "type",
          "type": "text",
          "primaryKey": false,
          "notNull": true,
          "autoincrement": false
        },
        "url": {
          "name": "url",
          "type": "text",
          "primaryKey": false,
          "notNull": true,
          "autoincrement": false
        },
        "enabled": {
          "name": "enabled",
          "type": "integer",
          "primaryKey": false,
          "notNull": true,
          "autoincrement": false,
          "default": true
        },
        "notify_on": {
          "name": "notify_on",
          "type": "text",
          "primaryKey": false,
          "notNull": true,
          "autoincrement": false,
          "default": "'[\"update_available\",\"import\",\"fail\"]'"
        }
      },
      "indexes": {},
      "foreignKeys": {},
      "compositePrimaryKeys": {},
      "uniqueConstraints": {},
      "checkConstraints": {}
    },
    "platforms": {
      "name": "platforms",
      "columns": {
        "id": {
          "name": "id",
          "type": "integer",
          "primaryKey": true,
          "notNull": true,
          "autoincrement": true
        },
        "name": {
          "name": "name",
          "type": "text",
          "primaryKey": false,
          "notNull": true,
          "autoincrement": false
        },
        "slug": {
          "name": "slug",
          "type": "text",
          "primaryKey": false,
          "notNull": true,
          "autoincrement": false
        },
        "file_extensions": {
          "name": "file_extensions",
          "type": "text",
          "primaryKey": false,
          "notNull": true,
          "autoincrement": false
        },
        "naming_standard": {
          "name": "naming_standard",
          "type": "text",
          "primaryKey": false,
          "notNull": true,
          "autoincrement": false,
          "default": "'none'"
        },
        "version_source": {
          "name": "version_source",
          "type": "text",
          "primaryKey": false,
          "notNull": true,
          "autoincrement": false,
          "default": "'none'"
        },
        "enabled": {
          "name": "enabled",
          "type": "integer",
          "primaryKey": false,
          "notNull": true,
          "autoincrement": false,
          "default": true
        },
        "torznab_categories": {
          "name": "torznab_categories",
          "type": "text",
          "primaryKey": false,
          "notNull": true,
          "autoincrement": false,
          "default": "'6000'"
        },
        "igdb_platform_id": {
          "name": "igdb_platform_id",
          "type": "integer",
          "primaryKey": false,
          "notNull": false,
          "autoincrement": false
        },
        "created_at": {
          "name": "created_at",
          "type": "text",
          "primaryKey": false,
          "notNull": true,
          "autoincrement": false,
          "default": "(datetime('now'))"
        }
      },
      "indexes": {
        "platforms_slug_unique": {
          "name": "platforms_slug_unique",
          "columns": [
            "slug"
          ],
          "isUnique": true
        }
      },
      "foreignKeys": {},
      "compositePrimaryKeys": {},
      "uniqueConstraints": {},
      "checkConstraints": {}
    },
    "quality_profiles": {
      "name": "quality_profiles",
      "columns": {
        "id": {
          "name": "id",
          "type": "integer",
          "primaryKey": true,
          "notNull": true,
          "autoincrement": true
        },
        "name": {
          "name": "name",
          "type": "text",
          "primaryKey": false,
          "notNull": true,
          "autoincrement": false
        },
        "platform_id": {
          "name": "platform_id",
          "type": "integer",
          "primaryKey": false,
          "notNull": true,
          "autoincrement": false
        },
        "preferred_formats": {
          "name": "preferred_formats",
          "type": "text",
          "primaryKey": false,
          "notNull": true,
          "autoincrement": false
        },
        "preferred_regions": {
          "name": "preferred_regions",
          "type": "text",
          "primaryKey": false,
          "notNull": true,
          "autoincrement": false
        },
        "min_seeders": {
          "name": "min_seeders",
          "type": "integer",
          "primaryKey": false,
          "notNull": true,
          "autoincrement": false,
          "default": 1
        },
        "upgrade_existing": {
          "name": "upgrade_existing",
          "type": "integer",
          "primaryKey": false,
          "notNull": true,
          "autoincrement": false,
          "default": false
        }
      },
      "indexes": {},
      "foreignKeys": {
        "quality_profiles_platform_id_platforms_id_fk": {
          "name": "quality_profiles_platform_id_platforms_id_fk",
          "tableFrom": "quality_profiles",
          "tableTo": "platforms",
          "columnsFrom": [
            "platform_id"
          ],
          "columnsTo": [
            "id"
          ],
          "onDelete": "no action",
          "onUpdate": "no action"
        }
      },
      "compositePrimaryKeys": {},
      "uniqueConstraints": {},
      "checkConstraints": {}
    },
    "search_history": {
      "name": "search_history",
      "columns": {
        "id": {
          "name": "id",
          "type": "integer",
          "primaryKey": true,
          "notNull": true,
          "autoincrement": true
        },
        "game_id": {
          "name": "game_id",
          "type": "integer",
          "primaryKey": false,
          "notNull": true,
          "autoincrement": false
        },
        "query_used": {
          "name": "query_used",
          "type": "text",
          "primaryKey": false,
          "notNull": true,
          "autoincrement": false
        },
        "indexer_id": {
          "name": "indexer_id",
          "type": "integer",
          "primaryKey": false,
          "notNull": false,
          "autoincrement": false
        },
        "results_count": {
          "name": "results_count",
          "type": "integer",
          "primaryKey": false,
          "notNull": true,
          "autoincrement": false,
          "default": 0
        },
        "best_score": {
          "name": "best_score",
          "type": "integer",
          "primaryKey": false,
          "notNull": false,
          "autoincrement": false
        },
        "searched_at": {
          "name": "searched_at",
          "type": "text",
          "primaryKey": false,
          "notNull": true,
          "autoincrement": false,
          "default": "(datetime('now'))"
        }
      },
      "indexes": {
        "search_history_game_id_idx": {
          "name": "search_history_game_id_idx",
          "columns": [
            "game_id"
          ],
          "isUnique": false
        }
      },
      "foreignKeys": {
        "search_history_game_id_games_id_fk": {
          "name": "search_history_game_id_games_id_fk",
          "tableFrom": "search_history",
          "tableTo": "games",
          "columnsFrom": [
            "game_id"
          ],
          "columnsTo": [
            "id"
          ],
          "onDelete": "no action",
          "onUpdate": "no action"
        },
        "search_history_indexer_id_indexers_id_fk": {
          "name": "search_history_indexer_id_indexers_id_fk",
          "tableFrom": "search_history",
          "tableTo": "indexers",
          "columnsFrom": [
            "indexer_id"
          ],
          "columnsTo": [
            "id"
          ],
          "onDelete": "no action",
          "onUpdate": "no action"
        }
      },
      "compositePrimaryKeys": {},
      "uniqueConstraints": {},
      "checkConstraints": {}
    },
    "settings": {
      "name": "settings",
      "columns": {
        "key": {
          "name": "key",
          "type": "text",
          "primaryKey": true,
          "notNull": true,
          "autoincrement": false
        },
        "value": {
          "name": "value",
          "type": "text",
          "primaryKey": false,
          "notNull": false,
          "autoincrement": false
        },
        "updated_at": {
          "name": "updated_at",
          "type": "text",
          "primaryKey": false,
          "notNull": true,
          "autoincrement": false,
          "default": "(datetime('now'))"
        }
      },
      "indexes": {},
      "foreignKeys": {},
      "compositePrimaryKeys": {},
      "uniqueConstraints": {},
      "checkConstraints": {}
    },
    "titledb_entries": {
      "name": "titledb_entries",
      "columns": {
        "id": {
          "name": "id",
          "type": "integer",
          "primaryKey": true,
          "notNull": true,
          "autoincrement": true
        },
        "version_source_id": {
          "name": "version_source_id",
          "type": "integer",
          "primaryKey": false,
          "notNull": true,
          "autoincrement": false
        },
        "title_id": {
          "name": "title_id",
          "type": "text",
          "primaryKey": false,
          "notNull": true,
          "autoincrement": false
        },
        "name": {
          "name": "name",
          "type": "text",
          "primaryKey": false,
          "notNull": false,
          "autoincrement": false
        },
        "version": {
          "name": "version",
          "type": "text",
          "primaryKey": false,
          "notNull": false,
          "autoincrement": false
        },
        "update_title_id": {
          "name": "update_title_id",
          "type": "text",
          "primaryKey": false,
          "notNull": false,
          "autoincrement": false
        },
        "dlc_title_ids": {
          "name": "dlc_title_ids",
          "type": "text",
          "primaryKey": false,
          "notNull": false,
          "autoincrement": false
        },
        "icon_url": {
          "name": "icon_url",
          "type": "text",
          "primaryKey": false,
          "notNull": false,
          "autoincrement": false
        },
        "publisher": {
          "name": "publisher",
          "type": "text",
          "primaryKey": false,
          "notNull": false,
          "autoincrement": false
        },
        "region": {
          "name": "region",
          "type": "text",
          "primaryKey": false,
          "notNull": false,
          "autoincrement": false
        }
      },
      "indexes": {
        "titledb_entries_version_source_id_idx": {
          "name": "titledb_entries_version_source_id_idx",
          "columns": [
            "version_source_id"
          ],
          "isUnique": false
        },
        "titledb_entries_title_id_idx": {
          "name": "titledb_entries_title_id_idx",
          "columns": [
            "title_id"
          ],
          "isUnique": false
        }
      },
      "foreignKeys": {
        "titledb_entries_version_source_id_version_sources_id_fk": {
          "name": "titledb_entries_version_source_id_version_sources_id_fk",
          "tableFrom": "titledb_entries",
          "tableTo": "version_sources",
          "columnsFrom": [
            "version_source_id"
          ],
          "columnsTo": [
            "id"
          ],
          "onDelete": "cascade",
          "onUpdate": "no action"
        }
      },
      "compositePrimaryKeys": {},
      "uniqueConstraints": {},
      "checkConstraints": {}
    },
    "users": {
      "name": "users",
      "columns": {
        "id": {
          "name": "id",
          "type": "integer",
          "primaryKey": true,
          "notNull": true,
          "autoincrement": true
        },
        "username": {
          "name": "username",
          "type": "text",
          "primaryKey": false,
          "notNull": true,
          "autoincrement": false
        },
        "password": {
          "name": "password",
          "type": "text",
          "primaryKey": false,
          "notNull": true,
          "autoincrement": false
        },
        "created_at": {
          "name": "created_at",
          "type": "text",
          "primaryKey": false,
          "notNull": true,
          "autoincrement": false,
          "default": "(datetime('now'))"
        }
      },
      "indexes": {
        "users_username_unique": {
          "name": "users_username_unique",
          "columns": [
            "username"
          ],
          "isUnique": true
        }
      },
      "foreignKeys": {},
      "compositePrimaryKeys": {},
      "uniqueConstraints": {},
      "checkConstraints": {}
    },
    "version_sources": {
      "name": "version_sources",
      "columns": {
        "id": {
          "name": "id",
          "type": "integer",
          "primaryKey": true,
          "notNull": true,
          "autoincrement": true
        },
        "platform_id": {
          "name": "platform_id",
          "type": "integer",
          "primaryKey": false,
          "notNull": true,
          "autoincrement": false
        },
        "source_type": {
          "name": "source_type",
          "type": "text",
          "primaryKey": false,
          "notNull": true,
          "autoincrement": false
        },
        "file_path": {
          "name": "file_path",
          "type": "text",
          "primaryKey": false,
          "notNull": false,
          "autoincrement": false
        },
        "url": {
          "name": "url",
          "type": "text",
          "primaryKey": false,
          "notNull": false,
          "autoincrement": false
        },
        "last_synced_at": {
          "name": "last_synced_at",
          "type": "text",
          "primaryKey": false,
          "notNull": false,
          "autoincrement": false
        },
        "entry_count": {
          "name": "entry_count",
          "type": "integer",
          "primaryKey": false,
          "notNull": false,
          "autoincrement": false,
          "default": 0
        }
      },
      "indexes": {
        "version_sources_platform_id_idx": {
          "name": "version_sources_platform_id_idx",
          "columns": [
            "platform_id"
          ],
          "isUnique": false
        }
      },
      "foreignKeys": {
        "version_sources_platform_id_platforms_id_fk": {
          "name": "version_sources_platform_id_platforms_id_fk",
          "tableFrom": "version_sources",
          "tableTo": "platforms",
          "columnsFrom": [
            "platform_id"
          ],
          "columnsTo": [
            "id"
          ],
          "onDelete": "no action",
          "onUpdate": "no action"
        }
      },
      "compositePrimaryKeys": {},
      "uniqueConstraints": {},
      "checkConstraints": {}
    },
    "wanted_games": {
      "name": "wanted_games",
      "columns": {
        "id": {
          "name": "id",
          "type": "integer",
          "primaryKey": true,
          "notNull": true,
          "autoincrement": true
        },
        "game_id": {
          "name": "game_id",
          "type": "integer",
          "primaryKey": false,
          "notNull": true,
          "autoincrement": false
        },
        "status": {
          "name": "status",
          "type": "text",
          "primaryKey": false,
          "notNull": true,
          "autoincrement": false,
          "default": "'wanted'"
        },
        "monitored": {
          "name": "monitored",
          "type": "integer",
          "primaryKey": false,
          "notNull": true,
          "autoincrement": false,
          "default": true
        },
        "quality_profile_id": {
          "name": "quality_profile_id",
          "type": "integer",
          "primaryKey": false,
          "notNull": false,
          "autoincrement": false
        },
        "added_at": {
          "name": "added_at",
          "type": "text",
          "primaryKey": false,
          "notNull": true,
          "autoincrement": false,
          "default": "(datetime('now'))"
        }
      },
      "indexes": {
        "wanted_games_game_id_unique": {
          "name": "wanted_games_game_id_unique",
          "columns": [
            "game_id"
          ],
          "isUnique": true
        },
        "wanted_games_status_idx": {
          "name": "wanted_games_status_idx",
          "columns": [
            "status"
          ],
          "isUnique": false
        },
        "wanted_games_game_id_idx": {
          "name": "wanted_games_game_id_idx",
          "columns": [
            "game_id"
          ],
          "isUnique": false
        }
      },
      "foreignKeys": {
        "wanted_games_game_id_games_id_fk": {
          "name": "wanted_games_game_id_games_id_fk",
          "tableFrom": "wanted_games",
          "tableTo": "games",
          "columnsFrom": [
            "game_id"
          ],
          "columnsTo": [
            "id"
          ],
          "onDelete": "cascade",
          "onUpdate": "no action"
        },
        "wanted_games_quality_profile_id_quality_profiles_id_fk": {
          "name": "wanted_games_quality_profile_id_quality_profiles_id_fk",
          "tableFrom": "wanted_games",
          "tableTo": "quality_profiles",
          "columnsFrom": [
            "quality_profile_id"
          ],
          "columnsTo": [
            "id"
          ],
          "onDelete": "no action",
          "onUpdate": "no action"
        }
      },
      "compositePrimaryKeys": {},
      "uniqueConstraints": {},
      "checkConstraints": {}
    }
  },
  "views": {},
  "enums": {},
  "_meta": {
    "schemas": {},
    "tables": {},
    "columns": {}
  },
  "internal": {
    "indexes": {}
  }
}